<?xml version="1.0" encoding="UTF-8"?>
<launch4jConfig>
  <dontWrapJar>false</dontWrapJar>
  <headerType>gui</headerType>
  <jar>D:\Desktop\Programing\Zodiac\ZodiacApp.jar</jar>
  <outfile>D:\Desktop\Programing\Zodiac\Zodiac.exe</outfile>
  <errTitle></errTitle>
  <cmdLine></cmdLine>
  <chdir>.</chdir>
  <priority>normal</priority>
  <downloadUrl>http://java.com/download</downloadUrl>
  <supportUrl></supportUrl>
  <stayAlive>false</stayAlive>
  <restartOnCrash>false</restartOnCrash>
  <manifest></manifest>
  <icon>D:\Desktop\Programing\Zodiac\lauch4j files\Zodiac-logo_transparent.ico</icon>
  <jre>
    <path></path>
    <bundledJre64Bit>false</bundledJre64Bit>
    <bundledJreAsFallback>false</bundledJreAsFallback>
    <minVersion>1.6.0</minVersion>
    <maxVersion></maxVersion>
    <jdkPreference>preferJre</jdkPreference>
    <runtimeBits>64/32</runtimeBits>
    <initialHeapSize>1024</initialHeapSize>
    <initialHeapPercent>25</initialHeapPercent>
    <maxHeapSize>3072</maxHeapSize>
    <maxHeapPercent>80</maxHeapPercent>
  </jre>
</launch4jConfig>